setup.cfg
setup.py
shelltest/__init__.py
shelltest/cli.py
shelltest/shelltest.py
shelltest/unittest.py
shelltest.egg-info/PKG-INFO
shelltest.egg-info/SOURCES.txt
shelltest.egg-info/dependency_links.txt
shelltest.egg-info/entry_points.txt
shelltest.egg-info/requires.txt
shelltest.egg-info/top_level.txt