Metadata-Version: 1.1
Name: shelltest
Version: 0.4.2
Summary: Shell tester
Home-page: https://github.com/jthacker/shelltest
Author: jthacker
Author-email: thacker.jon@gmail.com
License: UNKNOWN
Download-URL: https://github.com/jthacker/shelltest/archive/v0.4.2.tar.gz
Keywords: shell,testing
Platform: UNKNOWN
